[{"image1": "IMG_2281", "image2": "IMG_2281", "comp_score": 66, "occurnences_score": 20, "placement_score": 8, "colour_score": 36, "person_score": 0}, {"image1": "IMG_2281", "image2": "IMG_6543", "comp_score": 19, "occurnences_score": 10, "placement_score": 0, "colour_score": 24, "person_score": 0}, {"image1": "IMG_2281", "image2": "IMG_6555", "comp_score": 40, "occurnences_score": 14, "placement_score": 0, "colour_score": 36, "person_score": 0}, {"image1": "IMG_2281", "image2": "IMG_6576", "comp_score": 28, "occurnences_score": 8, "placement_score": 0, "colour_score": 45, "person_score": 0}, {"image1": "IMG_6543", "image2": "IMG_6543", "comp_score": 56, "occurnences_score": 18, "placement_score": 15, "colour_score": 24, "person_score": 0}, {"image1": "IMG_6543", "image2": "IMG_6555", "comp_score": 36, "occurnences_score": 10, "placement_score": 19, "colour_score": 18, "person_score": 0}, {"image1": "IMG_6543", "image2": "IMG_6576", "comp_score": 32, "occurnences_score": 4, "placement_score": 0, "colour_score": 45, "person_score": 0}, {"image1": "IMG_6555", "image2": "IMG_6555", "comp_score": 91, "occurnences_score": 18, "placement_score": 43, "colour_score": 36, "person_score": 0}, {"image1": "IMG_6555", "image2": "IMG_6576", "comp_score": 29, "occurnences_score": 6, "placement_score": 0, "colour_score": 51, "person_score": 0}, {"image1": "IMG_6576", "image2": "IMG_6576", "comp_score": 584, "occurnences_score": 18, "placement_score": 43, "colour_score": 444, "person_score": 0}]